<?xml version = "1.0" encoding = "UTF-8"?>
<INPUT>
<MEDALS>
    <MEDAL Id="gold" MEDAL_THRESHOLD="54000"><![CDATA[Gold]]></MEDAL>
	<MEDAL Id="silver" MEDAL_THRESHOLD="32000"><![CDATA[Silver]]></MEDAL>
	<MEDAL Id="bronze" MEDAL_THRESHOLD="28000"><![CDATA[Bronze]]></MEDAL>
</MEDALS>
<GAME_DATA>
<MESSAGES>
		<MESSAGES_EVENT type="start">
			<MESSAGE id="1">
				<TEXT_MSG><![CDATA[Start1]]></TEXT_MSG>
				<AUDIO_MSG><![CDATA[fluency/games/ft3_jungle/assets/audio/Start.mp3]]></AUDIO_MSG>
			</MESSAGE>

		</MESSAGES_EVENT>
		<MESSAGES_EVENT type="jump">
			<MESSAGE id="1">
				<TEXT_MSG><![CDATA[Jump1]]></TEXT_MSG>
				<AUDIO_MSG><![CDATA[fluency/games/ft3_jungle/assets/audio/No_sound.mp3]]></AUDIO_MSG>
			</MESSAGE>

		</MESSAGES_EVENT>
		<MESSAGES_EVENT type="correct_accum">
			<MESSAGE id="1">
				<TEXT_MSG><![CDATA[All right!]]></TEXT_MSG>
				<AUDIO_MSG><![CDATA[fluency/games/ft3_jungle/assets/audio/correct_accum1.mp3]]></AUDIO_MSG>
			</MESSAGE>
			<MESSAGE id="2">
				<TEXT_MSG><![CDATA[Yummy!]]></TEXT_MSG>
				<AUDIO_MSG><![CDATA[fluency/games/ft3_jungle/assets/audio/correct_accum2.mp3]]></AUDIO_MSG>
			</MESSAGE>

		</MESSAGES_EVENT>
		<MESSAGES_EVENT type="correct_avoid">
			<MESSAGE id="1">
				<TEXT_MSG><![CDATA[Good choice!]]></TEXT_MSG>
				<AUDIO_MSG><![CDATA[fluency/games/ft3_jungle/assets/audio/correct_avoid1.mp3]]></AUDIO_MSG>
			</MESSAGE>

		</MESSAGES_EVENT>
		<MESSAGES_EVENT type="incorrect_accum">
			<MESSAGE id="1">
				<TEXT_MSG><![CDATA[Uh!]]></TEXT_MSG>
				<AUDIO_MSG><![CDATA[fluency/games/ft3_jungle/assets/audio/incorrect_accum1.mp3]]></AUDIO_MSG>
			</MESSAGE>

		</MESSAGES_EVENT>
		<MESSAGES_EVENT type="incorrect_avoid">
			<MESSAGE id="1">
				<TEXT_MSG><![CDATA[You missed a good one!]]></TEXT_MSG>
				<AUDIO_MSG><![CDATA[fluency/games/ft3_jungle/assets/audio/incorrect_avoid1.mp3]]></AUDIO_MSG>
			</MESSAGE>

		</MESSAGES_EVENT>
		<MESSAGES_EVENT type="background">
			<MESSAGE id="1">
				<TEXT_MSG><![CDATA[background1]]></TEXT_MSG>
				<AUDIO_MSG><![CDATA[fluency/games/ft3_jungle/assets/audio/Background.mp3]]></AUDIO_MSG>
			</MESSAGE>

		</MESSAGES_EVENT>
		<MESSAGES_EVENT type="interlude">
			<MESSAGE id="1">
				<TEXT_MSG><![CDATA[Interlude1]]></TEXT_MSG>
				<AUDIO_MSG><![CDATA[fluency/games/ft3_jungle/assets/audio/interlude.mp3]]></AUDIO_MSG>
			</MESSAGE>

	</MESSAGES_EVENT>
		<MESSAGES_EVENT type="medal">
			<MESSAGE id="1">
				<TEXT_MSG><![CDATA[You earned a medal!]]></TEXT_MSG>
				<AUDIO_MSG><![CDATA[fluency/games/ft3_jungle/assets/audio/medal.mp3]]></AUDIO_MSG>
			</MESSAGE>

		</MESSAGES_EVENT>
		<MESSAGES_EVENT type="end">
			<MESSAGE id="1">
				<TEXT_MSG><![CDATA[Game over.]]></TEXT_MSG>
				<AUDIO_MSG><![CDATA[fluency/games/ft3_jungle/assets/audio/End.mp3]]></AUDIO_MSG>
			</MESSAGE>

		</MESSAGES_EVENT>
		<MESSAGES_EVENT type="new">
			<MESSAGE id="1">
				<TEXT_MSG><![CDATA[new]]></TEXT_MSG>
				<AUDIO_MSG><![CDATA[fluency/games/ft3_jungle/assets/audio/No_sound.mp3]]></AUDIO_MSG>
			</MESSAGE>

		</MESSAGES_EVENT>
</MESSAGES>
	<CORRECT ACCUMULATE="2000" AVOID="2000" /> 
	<INCORRECT ACCUMULATE="-100" AVOID="-100" /> 
	<BONUS_REMAINING_LIFE VALUE="5000" />
	<LIVES ACCUM_IMPACT="-1" AVOID_IMPACT="-1" TOTAL="3" />
	<GRAVITY VALUE="true" />
	<BASE_LANE VALUE="0" />
	<COMMIT_AREA VALUE="70" />
	<RANDOM_SEED VALUE="351" />
<PROBLEM_SET>
		<PROBLEM_SUBSET TIME_PER_QUESTION="2000">
			<TARGET ID="1" Type="Text" Value="Unsimplified Fractions"> 
 
			</TARGET>
			<QUESTION ANSWER="1" ID="1" PLATFORM="true">
				<QUESTION Lane="1" Type="Image" Value="100/22">
		<DISPLAY><![CDATA[fluency/data/images/b197eaa5376c87a51b884690d4b1256d.png]]></DISPLAY> 
				</QUESTION>
			</QUESTION>
			<QUESTION ANSWER="0" ID="2" PLATFORM="true">
				<QUESTION Lane="0" Type="Image" Value="32/50">
		<DISPLAY><![CDATA[fluency/data/images/25ab1ada5c6ac9d7fbf9dde0824f2027.png]]></DISPLAY> 
				</QUESTION>
			</QUESTION>
			<QUESTION ANSWER="1" ID="3" PLATFORM="true">
				<QUESTION Lane="1" Type="Image" Value="35/56">
		<DISPLAY><![CDATA[fluency/data/images/104222b47412a4b79f8ee9799c157ffd.png]]></DISPLAY> 
				</QUESTION>
			</QUESTION>
			<QUESTION ANSWER="1" ID="4" PLATFORM="true">
				<QUESTION Lane="1" Type="Image" Value="72/20">
		<DISPLAY><![CDATA[fluency/data/images/6fdb3eed82a9d83e1f2bc1ccf7e5b51f.png]]></DISPLAY> 
				</QUESTION>
			</QUESTION>
			<QUESTION ANSWER="0" ID="5" PLATFORM="true">
				<QUESTION Lane="0" Type="Image" Value="2/90">
		<DISPLAY><![CDATA[fluency/data/images/5af5465af840a7e5e7d40afe3d497d63.png]]></DISPLAY> 
				</QUESTION>
			</QUESTION>
			<QUESTION ANSWER="0" ID="6" PLATFORM="true">
				<QUESTION Lane="1" Type="Image" Value="7/40">
		<DISPLAY><![CDATA[fluency/data/images/e20782b68a77fcd71bc6982b35352216.png]]></DISPLAY> 
				</QUESTION>
			</QUESTION>
			<QUESTION ANSWER="0" ID="7" PLATFORM="true">
				<QUESTION Lane="0" Type="Image" Value="120/15">
		<DISPLAY><![CDATA[fluency/data/images/07402f10d384dc0cee30e27240c83d81.png]]></DISPLAY> 
				</QUESTION>
			</QUESTION>
			<QUESTION ANSWER="0" ID="8" PLATFORM="true">
				<QUESTION Lane="1" Type="Image" Value="7/12">
		<DISPLAY><![CDATA[fluency/data/images/0c9a49fc084bb1eb53fc4e68c11a8e9a.png]]></DISPLAY> 
				</QUESTION>
			</QUESTION>
			<QUESTION ANSWER="1" ID="9" PLATFORM="true">
				<QUESTION Lane="1" Type="Image" Value="10/84">
		<DISPLAY><![CDATA[fluency/data/images/3a9778d194a82626721828144b3f90b2.png]]></DISPLAY> 
				</QUESTION>
			</QUESTION>
			<QUESTION ANSWER="1" ID="10" PLATFORM="true">
				<QUESTION Lane="1" Type="Image" Value="2/8">
		<DISPLAY><![CDATA[fluency/data/images/4671eeda5c1c4b237753d6a02626bbb5.png]]></DISPLAY> 
				</QUESTION>
			</QUESTION>
		</PROBLEM_SUBSET>
		<PROBLEM_SUBSET TIME_PER_QUESTION="1500">
			<TARGET ID="2" Type="Text" Value="Simplified Fractions"> 
 
			</TARGET>
			<QUESTION ANSWER="1" ID="1" PLATFORM="true">
				<QUESTION Lane="0" Type="Image" Value="60/50">
		<DISPLAY><![CDATA[fluency/data/images/5e1f5fd78d871213ef43b16651c77888.png]]></DISPLAY> 
				</QUESTION>
			</QUESTION>
			<QUESTION ANSWER="1" ID="2" PLATFORM="true">
				<QUESTION Lane="0" Type="Image" Value="27/36">
		<DISPLAY><![CDATA[fluency/data/images/3458cb298613fd110373e57fa8e88422.png]]></DISPLAY> 
				</QUESTION>
			</QUESTION>
			<QUESTION ANSWER="0" ID="3" PLATFORM="true">
				<QUESTION Lane="1" Type="Image" Value="15/18">
		<DISPLAY><![CDATA[fluency/data/images/9f6752ceb56a313d16cd1641a3c69a79.png]]></DISPLAY> 
				</QUESTION>
			</QUESTION>
			<QUESTION ANSWER="0" ID="4" PLATFORM="true">
				<QUESTION Lane="1" Type="Image" Value="72/12">
		<DISPLAY><![CDATA[fluency/data/images/395fa2d987e1f2ef60711151f7ec7e99.png]]></DISPLAY> 
				</QUESTION>
			</QUESTION>
			<QUESTION ANSWER="1" ID="5" PLATFORM="true">
				<QUESTION Lane="0" Type="Image" Value="30/50">
		<DISPLAY><![CDATA[fluency/data/images/f1d1b82e2e85a5b289f23a3878c88114.png]]></DISPLAY> 
				</QUESTION>
			</QUESTION>
			<QUESTION ANSWER="0" ID="6" PLATFORM="true">
				<QUESTION Lane="1" Type="Image" Value="20/44">
		<DISPLAY><![CDATA[fluency/data/images/c3652214afb9348833136d97edbcca68.png]]></DISPLAY> 
				</QUESTION>
			</QUESTION>
			<QUESTION ANSWER="1" ID="7" PLATFORM="true">
				<QUESTION Lane="1" Type="Image" Value="35/32">
		<DISPLAY><![CDATA[fluency/data/images/c28f0dfd23557f9a4975692167aff906.png]]></DISPLAY> 
				</QUESTION>
			</QUESTION>
			<QUESTION ANSWER="1" ID="8" PLATFORM="true">
				<QUESTION Lane="0" Type="Image" Value="99/108">
		<DISPLAY><![CDATA[fluency/data/images/9283f29c17dc9012d03192492eb503b8.png]]></DISPLAY> 
				</QUESTION>
			</QUESTION>
			<QUESTION ANSWER="0" ID="9" PLATFORM="true">
				<QUESTION Lane="1" Type="Image" Value="12/60">
		<DISPLAY><![CDATA[fluency/data/images/1d0d65b16be11174f552918ea8bd64b9.png]]></DISPLAY> 
				</QUESTION>
			</QUESTION>
			<QUESTION ANSWER="0" ID="10" PLATFORM="true">
				<QUESTION Lane="1" Type="Image" Value="96/56">
		<DISPLAY><![CDATA[fluency/data/images/5f66e82c795b8dbf9d0ae57c42c5a260.png]]></DISPLAY> 
				</QUESTION>
			</QUESTION>
		</PROBLEM_SUBSET>
		<PROBLEM_SUBSET TIME_PER_QUESTION="2500">
			<TARGET ID="3" Type="Text" Value="Unsimplified Fractions"> 
 
			</TARGET>
			<QUESTION ANSWER="0" ID="1" PLATFORM="true">
				<QUESTION Lane="0" Type="Image" Value="80/30">
		<DISPLAY><![CDATA[fluency/data/images/0308b10214362a04d136876dd9491fc5.png]]></DISPLAY> 
				</QUESTION>
			</QUESTION>
			<QUESTION ANSWER="0" ID="2" PLATFORM="true">
				<QUESTION Lane="0" Type="Image" Value="4/90">
		<DISPLAY><![CDATA[fluency/data/images/9e9f3cf64c8b5aeb6c3b491f840e838d.png]]></DISPLAY> 
				</QUESTION>
			</QUESTION>
			<QUESTION ANSWER="0" ID="3" PLATFORM="true">
				<QUESTION Lane="1" Type="Image" Value="9/8">
		<DISPLAY><![CDATA[fluency/data/images/e93cad6423d31748265706e535802a02.png]]></DISPLAY> 
				</QUESTION>
			</QUESTION>
			<QUESTION ANSWER="0" ID="4" PLATFORM="true">
				<QUESTION Lane="0" Type="Image" Value="20/20">
		<DISPLAY><![CDATA[fluency/data/images/0dffa556f2597d99fdebc3fc0ca22e52.png]]></DISPLAY> 
				</QUESTION>
			</QUESTION>
			<QUESTION ANSWER="1" ID="5" PLATFORM="true">
				<QUESTION Lane="1" Type="Image" Value="12/20">
		<DISPLAY><![CDATA[fluency/data/images/90a27bebdb5c345d36dfe780ff19dc23.png]]></DISPLAY> 
				</QUESTION>
			</QUESTION>
			<QUESTION ANSWER="1" ID="6" PLATFORM="true">
				<QUESTION Lane="1" Type="Image" Value="6/90">
		<DISPLAY><![CDATA[fluency/data/images/7915c52048cb153ab9ba552b5bad2264.png]]></DISPLAY> 
				</QUESTION>
			</QUESTION>
			<QUESTION ANSWER="0" ID="7" PLATFORM="true">
				<QUESTION Lane="0" Type="Image" Value="32/12">
		<DISPLAY><![CDATA[fluency/data/images/a526e794f6099d869a053df374456b60.png]]></DISPLAY> 
				</QUESTION>
			</QUESTION>
			<QUESTION ANSWER="1" ID="8" PLATFORM="true">
				<QUESTION Lane="1" Type="Image" Value="18/54">
		<DISPLAY><![CDATA[fluency/data/images/78a08c9d86e8282723589a492538cc74.png]]></DISPLAY> 
				</QUESTION>
			</QUESTION>
			<QUESTION ANSWER="0" ID="9" PLATFORM="true">
				<QUESTION Lane="0" Type="Image" Value="8/24">
		<DISPLAY><![CDATA[fluency/data/images/ada28df62f9eb5696981c204125f6412.png]]></DISPLAY> 
				</QUESTION>
			</QUESTION>
			<QUESTION ANSWER="1" ID="10" PLATFORM="true">
				<QUESTION Lane="1" Type="Image" Value="90/99">
		<DISPLAY><![CDATA[fluency/data/images/6d0096c463e1ef1ee985ba9569fb698e.png]]></DISPLAY> 
				</QUESTION>
			</QUESTION>
		</PROBLEM_SUBSET>
		<PROBLEM_SUBSET TIME_PER_QUESTION="2000">
			<TARGET ID="4" Type="Text" Value="Simplified Fractions"> 
 
			</TARGET>
			<QUESTION ANSWER="1" ID="1" PLATFORM="true">
				<QUESTION Lane="0" Type="Image" Value="40/12">
		<DISPLAY><![CDATA[fluency/data/images/5c9e157cff70b16d8b8435878cf80830.png]]></DISPLAY> 
				</QUESTION>
			</QUESTION>
			<QUESTION ANSWER="1" ID="2" PLATFORM="true">
				<QUESTION Lane="1" Type="Image" Value="9/55">
		<DISPLAY><![CDATA[fluency/data/images/663945dd9a0bdee10423eb2cc1bfe878.png]]></DISPLAY> 
				</QUESTION>
			</QUESTION>
			<QUESTION ANSWER="1" ID="3" PLATFORM="true">
				<QUESTION Lane="0" Type="Image" Value="63/28">
		<DISPLAY><![CDATA[fluency/data/images/aaffbdf7491a4d72141f5509927d6489.png]]></DISPLAY> 
				</QUESTION>
			</QUESTION>
			<QUESTION ANSWER="0" ID="4" PLATFORM="true">
				<QUESTION Lane="1" Type="Image" Value="4/28">
		<DISPLAY><![CDATA[fluency/data/images/0fd45ced9884d19d1ab73d8e7d0d76a2.png]]></DISPLAY> 
				</QUESTION>
			</QUESTION>
			<QUESTION ANSWER="0" ID="5" PLATFORM="true">
				<QUESTION Lane="1" Type="Image" Value="10/8">
		<DISPLAY><![CDATA[fluency/data/images/39be3885e0c6ad4231e7f31f38d98f53.png]]></DISPLAY> 
				</QUESTION>
			</QUESTION>
			<QUESTION ANSWER="0" ID="6" PLATFORM="true">
				<QUESTION Lane="0" Type="Image" Value="5/12">
		<DISPLAY><![CDATA[fluency/data/images/7070377275d84daf14cf17948f056700.png]]></DISPLAY> 
				</QUESTION>
			</QUESTION>
			<QUESTION ANSWER="0" ID="7" PLATFORM="true">
				<QUESTION Lane="1" Type="Image" Value="63/12">
		<DISPLAY><![CDATA[fluency/data/images/b0923ea94df6622fb9fd02e3fa6ce73b.png]]></DISPLAY> 
				</QUESTION>
			</QUESTION>
			<QUESTION ANSWER="0" ID="8" PLATFORM="true">
				<QUESTION Lane="1" Type="Image" Value="88/12">
		<DISPLAY><![CDATA[fluency/data/images/eb960643864bcf699e54049ae660ac22.png]]></DISPLAY> 
				</QUESTION>
			</QUESTION>
			<QUESTION ANSWER="1" ID="9" PLATFORM="true">
				<QUESTION Lane="0" Type="Image" Value="48/90">
		<DISPLAY><![CDATA[fluency/data/images/7222c94c48dcd00ae1ec0f08b981cfab.png]]></DISPLAY> 
				</QUESTION>
			</QUESTION>
			<QUESTION ANSWER="0" ID="10" PLATFORM="true">
				<QUESTION Lane="1" Type="Image" Value="12/40">
		<DISPLAY><![CDATA[fluency/data/images/4e720635bdb32bdf0b30136cd7f16cea.png]]></DISPLAY> 
				</QUESTION>
			</QUESTION>
		</PROBLEM_SUBSET>
 </PROBLEM_SET>

</GAME_DATA>
</INPUT>