<?xml version = "1.0" encoding = "UTF-8"?>
<INPUT>
<MEDALS>
    <MEDAL Id="gold" MEDAL_THRESHOLD="54000"><![CDATA[Gold]]></MEDAL>
	<MEDAL Id="silver" MEDAL_THRESHOLD="32000"><![CDATA[Silver]]></MEDAL>
	<MEDAL Id="bronze" MEDAL_THRESHOLD="28000"><![CDATA[Bronze]]></MEDAL>
</MEDALS>
<GAME_DATA>
<MESSAGES>
		<MESSAGES_EVENT type="start">
			<MESSAGE id="1">
				<TEXT_MSG><![CDATA[Start1]]></TEXT_MSG>
				<AUDIO_MSG><![CDATA[fluency/games/ft3_jungle/assets/audio/Start.mp3]]></AUDIO_MSG>
			</MESSAGE>

		</MESSAGES_EVENT>
		<MESSAGES_EVENT type="jump">
			<MESSAGE id="1">
				<TEXT_MSG><![CDATA[Jump1]]></TEXT_MSG>
				<AUDIO_MSG><![CDATA[fluency/games/ft3_jungle/assets/audio/No_sound.mp3]]></AUDIO_MSG>
			</MESSAGE>

		</MESSAGES_EVENT>
		<MESSAGES_EVENT type="correct_accum">
			<MESSAGE id="1">
				<TEXT_MSG><![CDATA[All right!]]></TEXT_MSG>
				<AUDIO_MSG><![CDATA[fluency/games/ft3_jungle/assets/audio/correct_accum1.mp3]]></AUDIO_MSG>
			</MESSAGE>
			<MESSAGE id="2">
				<TEXT_MSG><![CDATA[Yummy!]]></TEXT_MSG>
				<AUDIO_MSG><![CDATA[fluency/games/ft3_jungle/assets/audio/correct_accum2.mp3]]></AUDIO_MSG>
			</MESSAGE>

		</MESSAGES_EVENT>
		<MESSAGES_EVENT type="correct_avoid">
			<MESSAGE id="1">
				<TEXT_MSG><![CDATA[Good choice!]]></TEXT_MSG>
				<AUDIO_MSG><![CDATA[fluency/games/ft3_jungle/assets/audio/correct_avoid1.mp3]]></AUDIO_MSG>
			</MESSAGE>

		</MESSAGES_EVENT>
		<MESSAGES_EVENT type="incorrect_accum">
			<MESSAGE id="1">
				<TEXT_MSG><![CDATA[Uh!]]></TEXT_MSG>
				<AUDIO_MSG><![CDATA[fluency/games/ft3_jungle/assets/audio/incorrect_accum1.mp3]]></AUDIO_MSG>
			</MESSAGE>

		</MESSAGES_EVENT>
		<MESSAGES_EVENT type="incorrect_avoid">
			<MESSAGE id="1">
				<TEXT_MSG><![CDATA[You missed a good one!]]></TEXT_MSG>
				<AUDIO_MSG><![CDATA[fluency/games/ft3_jungle/assets/audio/incorrect_avoid1.mp3]]></AUDIO_MSG>
			</MESSAGE>

		</MESSAGES_EVENT>
		<MESSAGES_EVENT type="background">
			<MESSAGE id="1">
				<TEXT_MSG><![CDATA[background1]]></TEXT_MSG>
				<AUDIO_MSG><![CDATA[fluency/games/ft3_jungle/assets/audio/Background.mp3]]></AUDIO_MSG>
			</MESSAGE>

		</MESSAGES_EVENT>
		<MESSAGES_EVENT type="interlude">
			<MESSAGE id="1">
				<TEXT_MSG><![CDATA[Interlude1]]></TEXT_MSG>
				<AUDIO_MSG><![CDATA[fluency/games/ft3_jungle/assets/audio/interlude.mp3]]></AUDIO_MSG>
			</MESSAGE>

	</MESSAGES_EVENT>
		<MESSAGES_EVENT type="medal">
			<MESSAGE id="1">
				<TEXT_MSG><![CDATA[You earned a medal!]]></TEXT_MSG>
				<AUDIO_MSG><![CDATA[fluency/games/ft3_jungle/assets/audio/medal.mp3]]></AUDIO_MSG>
			</MESSAGE>

		</MESSAGES_EVENT>
		<MESSAGES_EVENT type="end">
			<MESSAGE id="1">
				<TEXT_MSG><![CDATA[Game over.]]></TEXT_MSG>
				<AUDIO_MSG><![CDATA[fluency/games/ft3_jungle/assets/audio/End.mp3]]></AUDIO_MSG>
			</MESSAGE>

		</MESSAGES_EVENT>
		<MESSAGES_EVENT type="new">
			<MESSAGE id="1">
				<TEXT_MSG><![CDATA[new]]></TEXT_MSG>
				<AUDIO_MSG><![CDATA[fluency/games/ft3_jungle/assets/audio/No_sound.mp3]]></AUDIO_MSG>
			</MESSAGE>

		</MESSAGES_EVENT>
</MESSAGES>
	<CORRECT ACCUMULATE="2000" AVOID="2000" /> 
	<INCORRECT ACCUMULATE="-100" AVOID="-100" /> 
	<BONUS_REMAINING_LIFE VALUE="5000" />
	<LIVES ACCUM_IMPACT="-1" AVOID_IMPACT="-1" TOTAL="3" />
	<GRAVITY VALUE="true" />
	<BASE_LANE VALUE="0" />
	<COMMIT_AREA VALUE="70" />
	<RANDOM_SEED VALUE="274" />
<PROBLEM_SET>
		<PROBLEM_SUBSET TIME_PER_QUESTION="2000">
			<TARGET ID="1" Type="Text" Value="Unsimplified Fractions"> 
 
			</TARGET>
			<QUESTION ANSWER="1" ID="1" PLATFORM="true">
				<QUESTION Lane="1" Type="Image" Value="40/36">
		<DISPLAY><![CDATA[fluency/data/images/e93dc02defe534d83c5bbf9ed7345e73.png]]></DISPLAY> 
				</QUESTION>
			</QUESTION>
			<QUESTION ANSWER="0" ID="2" PLATFORM="true">
				<QUESTION Lane="1" Type="Image" Value="21/8">
		<DISPLAY><![CDATA[fluency/data/images/4886dbc0e006eb755edc6ffdd3ffd779.png]]></DISPLAY> 
				</QUESTION>
			</QUESTION>
			<QUESTION ANSWER="1" ID="3" PLATFORM="true">
				<QUESTION Lane="1" Type="Image" Value="110/6">
		<DISPLAY><![CDATA[fluency/data/images/04fe8fd23d052e74f528039d9b32843b.png]]></DISPLAY> 
				</QUESTION>
			</QUESTION>
			<QUESTION ANSWER="1" ID="4" PLATFORM="true">
				<QUESTION Lane="1" Type="Image" Value="20/20">
		<DISPLAY><![CDATA[fluency/data/images/0dffa556f2597d99fdebc3fc0ca22e52.png]]></DISPLAY> 
				</QUESTION>
			</QUESTION>
			<QUESTION ANSWER="1" ID="5" PLATFORM="true">
				<QUESTION Lane="1" Type="Image" Value="80/12">
		<DISPLAY><![CDATA[fluency/data/images/140f8606eaaba1c2ca597cc276c1db01.png]]></DISPLAY> 
				</QUESTION>
			</QUESTION>
			<QUESTION ANSWER="1" ID="6" PLATFORM="true">
				<QUESTION Lane="1" Type="Image" Value="36/16">
		<DISPLAY><![CDATA[fluency/data/images/289c9b1f79fb3e2cb1b068f80a220120.png]]></DISPLAY> 
				</QUESTION>
			</QUESTION>
			<QUESTION ANSWER="0" ID="7" PLATFORM="true">
				<QUESTION Lane="0" Type="Image" Value="8/42">
		<DISPLAY><![CDATA[fluency/data/images/966d646da903abb9d9c836f047e3db29.png]]></DISPLAY> 
				</QUESTION>
			</QUESTION>
			<QUESTION ANSWER="0" ID="8" PLATFORM="true">
				<QUESTION Lane="0" Type="Image" Value="15/9">
		<DISPLAY><![CDATA[fluency/data/images/58712ebd8911cd9eb7a2c01bc784339a.png]]></DISPLAY> 
				</QUESTION>
			</QUESTION>
			<QUESTION ANSWER="0" ID="9" PLATFORM="true">
				<QUESTION Lane="0" Type="Image" Value="110/30">
		<DISPLAY><![CDATA[fluency/data/images/589a0bdd1a5144f4ee244607f5810ff2.png]]></DISPLAY> 
				</QUESTION>
			</QUESTION>
			<QUESTION ANSWER="0" ID="10" PLATFORM="true">
				<QUESTION Lane="0" Type="Image" Value="50/24">
		<DISPLAY><![CDATA[fluency/data/images/1ca309ee1a7f24ffa2a6f23f64e0b8d7.png]]></DISPLAY> 
				</QUESTION>
			</QUESTION>
		</PROBLEM_SUBSET>
		<PROBLEM_SUBSET TIME_PER_QUESTION="1500">
			<TARGET ID="2" Type="Text" Value="Simplified Fractions"> 
 
			</TARGET>
			<QUESTION ANSWER="0" ID="1" PLATFORM="true">
				<QUESTION Lane="1" Type="Image" Value="60/108">
		<DISPLAY><![CDATA[fluency/data/images/8e1103cc8ad2253ff16b9f722fbaa0b7.png]]></DISPLAY> 
				</QUESTION>
			</QUESTION>
			<QUESTION ANSWER="0" ID="2" PLATFORM="true">
				<QUESTION Lane="1" Type="Image" Value="30/16">
		<DISPLAY><![CDATA[fluency/data/images/6d7078281222cc6b3cefe6afa6e322ac.png]]></DISPLAY> 
				</QUESTION>
			</QUESTION>
			<QUESTION ANSWER="1" ID="3" PLATFORM="true">
				<QUESTION Lane="1" Type="Image" Value="99/100">
		<DISPLAY><![CDATA[fluency/data/images/b2004929eae043043d85dfa100242b1b.png]]></DISPLAY> 
				</QUESTION>
			</QUESTION>
			<QUESTION ANSWER="0" ID="4" PLATFORM="true">
				<QUESTION Lane="1" Type="Image" Value="72/70">
		<DISPLAY><![CDATA[fluency/data/images/c7ce198f89555d55c1b17051d92c45f9.png]]></DISPLAY> 
				</QUESTION>
			</QUESTION>
			<QUESTION ANSWER="0" ID="5" PLATFORM="true">
				<QUESTION Lane="1" Type="Image" Value="3/45">
		<DISPLAY><![CDATA[fluency/data/images/350980377f6551e90fba926739062d1e.png]]></DISPLAY> 
				</QUESTION>
			</QUESTION>
			<QUESTION ANSWER="0" ID="6" PLATFORM="true">
				<QUESTION Lane="1" Type="Image" Value="28/63">
		<DISPLAY><![CDATA[fluency/data/images/20f38df0e8c5a4defb8695d21b9357bf.png]]></DISPLAY> 
				</QUESTION>
			</QUESTION>
			<QUESTION ANSWER="1" ID="7" PLATFORM="true">
				<QUESTION Lane="0" Type="Image" Value="110/80">
		<DISPLAY><![CDATA[fluency/data/images/305382e6974fd6cfa87275694c129954.png]]></DISPLAY> 
				</QUESTION>
			</QUESTION>
			<QUESTION ANSWER="0" ID="8" PLATFORM="true">
				<QUESTION Lane="0" Type="Image" Value="3/100">
		<DISPLAY><![CDATA[fluency/data/images/aaaa6dad20216d05d3262d791057ebd7.png]]></DISPLAY> 
				</QUESTION>
			</QUESTION>
			<QUESTION ANSWER="0" ID="9" PLATFORM="true">
				<QUESTION Lane="1" Type="Image" Value="54/20">
		<DISPLAY><![CDATA[fluency/data/images/bf7c2c1fd6d3e3ffb87cffe3b38860c4.png]]></DISPLAY> 
				</QUESTION>
			</QUESTION>
			<QUESTION ANSWER="0" ID="10" PLATFORM="true">
				<QUESTION Lane="0" Type="Image" Value="10/11">
		<DISPLAY><![CDATA[fluency/data/images/f129788f999a0c79f35e361d6a739104.png]]></DISPLAY> 
				</QUESTION>
			</QUESTION>
		</PROBLEM_SUBSET>
		<PROBLEM_SUBSET TIME_PER_QUESTION="2500">
			<TARGET ID="3" Type="Text" Value="Unsimplified Fractions"> 
 
			</TARGET>
			<QUESTION ANSWER="1" ID="1" PLATFORM="true">
				<QUESTION Lane="1" Type="Image" Value="48/70">
		<DISPLAY><![CDATA[fluency/data/images/50876c2ca115a89694eb70aceeff9516.png]]></DISPLAY> 
				</QUESTION>
			</QUESTION>
			<QUESTION ANSWER="1" ID="2" PLATFORM="true">
				<QUESTION Lane="1" Type="Image" Value="70/20">
		<DISPLAY><![CDATA[fluency/data/images/45cf6aa7ee36e96074f13ec8e7d75cc3.png]]></DISPLAY> 
				</QUESTION>
			</QUESTION>
			<QUESTION ANSWER="1" ID="3" PLATFORM="true">
				<QUESTION Lane="1" Type="Image" Value="48/6">
		<DISPLAY><![CDATA[fluency/data/images/9d94059be1ab340e7284d276ecfe46a4.png]]></DISPLAY> 
				</QUESTION>
			</QUESTION>
			<QUESTION ANSWER="0" ID="4" PLATFORM="true">
				<QUESTION Lane="1" Type="Image" Value="88/49">
		<DISPLAY><![CDATA[fluency/data/images/5ff3c37982658100f4eb274903a83210.png]]></DISPLAY> 
				</QUESTION>
			</QUESTION>
			<QUESTION ANSWER="0" ID="5" PLATFORM="true">
				<QUESTION Lane="1" Type="Image" Value="33/8">
		<DISPLAY><![CDATA[fluency/data/images/23d87c4ce0b7fcda160b31f52c693570.png]]></DISPLAY> 
				</QUESTION>
			</QUESTION>
			<QUESTION ANSWER="0" ID="6" PLATFORM="true">
				<QUESTION Lane="0" Type="Image" Value="10/50">
		<DISPLAY><![CDATA[fluency/data/images/6db3cc4ca7819ec0fefb06ce90f91f25.png]]></DISPLAY> 
				</QUESTION>
			</QUESTION>
			<QUESTION ANSWER="1" ID="7" PLATFORM="true">
				<QUESTION Lane="0" Type="Image" Value="77/6">
		<DISPLAY><![CDATA[fluency/data/images/d3156f04c6752a817a84f15346efd63c.png]]></DISPLAY> 
				</QUESTION>
			</QUESTION>
			<QUESTION ANSWER="0" ID="8" PLATFORM="true">
				<QUESTION Lane="0" Type="Image" Value="2/108">
		<DISPLAY><![CDATA[fluency/data/images/d5cebeb1b4b144da7240366a6db432d3.png]]></DISPLAY> 
				</QUESTION>
			</QUESTION>
			<QUESTION ANSWER="0" ID="9" PLATFORM="true">
				<QUESTION Lane="0" Type="Image" Value="10/15">
		<DISPLAY><![CDATA[fluency/data/images/5c2985808f6536cee0b9af8d0dee1e7e.png]]></DISPLAY> 
				</QUESTION>
			</QUESTION>
			<QUESTION ANSWER="1" ID="10" PLATFORM="true">
				<QUESTION Lane="0" Type="Image" Value="4/5">
		<DISPLAY><![CDATA[fluency/data/images/fe40642782cb7ab5ee480932cfe38ff6.png]]></DISPLAY> 
				</QUESTION>
			</QUESTION>
		</PROBLEM_SUBSET>
		<PROBLEM_SUBSET TIME_PER_QUESTION="2000">
			<TARGET ID="4" Type="Text" Value="Simplified Fractions"> 
 
			</TARGET>
			<QUESTION ANSWER="0" ID="1" PLATFORM="true">
				<QUESTION Lane="1" Type="Image" Value="10/55">
		<DISPLAY><![CDATA[fluency/data/images/8f3cf6596ad27a587d2e4a72ddc39190.png]]></DISPLAY> 
				</QUESTION>
			</QUESTION>
			<QUESTION ANSWER="1" ID="2" PLATFORM="true">
				<QUESTION Lane="0" Type="Image" Value="110/70">
		<DISPLAY><![CDATA[fluency/data/images/3b1489e84dd5c983e7b44123de499d85.png]]></DISPLAY> 
				</QUESTION>
			</QUESTION>
			<QUESTION ANSWER="1" ID="3" PLATFORM="true">
				<QUESTION Lane="0" Type="Image" Value="36/14">
		<DISPLAY><![CDATA[fluency/data/images/707fcbabec4cc79feefea6369adaad46.png]]></DISPLAY> 
				</QUESTION>
			</QUESTION>
			<QUESTION ANSWER="1" ID="4" PLATFORM="true">
				<QUESTION Lane="0" Type="Image" Value="36/9">
		<DISPLAY><![CDATA[fluency/data/images/c5200ae1bfa359bbf562ee570a185375.png]]></DISPLAY> 
				</QUESTION>
			</QUESTION>
			<QUESTION ANSWER="0" ID="5" PLATFORM="true">
				<QUESTION Lane="1" Type="Image" Value="20/12">
		<DISPLAY><![CDATA[fluency/data/images/89e41db44fe3b3c286dd641b72a206cb.png]]></DISPLAY> 
				</QUESTION>
			</QUESTION>
			<QUESTION ANSWER="1" ID="6" PLATFORM="true">
				<QUESTION Lane="0" Type="Image" Value="96/6">
		<DISPLAY><![CDATA[fluency/data/images/6212a3dae6edb0af30cef6ac0e3e55a6.png]]></DISPLAY> 
				</QUESTION>
			</QUESTION>
			<QUESTION ANSWER="0" ID="7" PLATFORM="true">
				<QUESTION Lane="1" Type="Image" Value="28/40">
		<DISPLAY><![CDATA[fluency/data/images/ce88fe437f189cd687eaf2bd8ca06ea8.png]]></DISPLAY> 
				</QUESTION>
			</QUESTION>
			<QUESTION ANSWER="0" ID="8" PLATFORM="true">
				<QUESTION Lane="1" Type="Image" Value="108/80">
		<DISPLAY><![CDATA[fluency/data/images/c2bdfe3435323b5704e25099db3a1dbd.png]]></DISPLAY> 
				</QUESTION>
			</QUESTION>
			<QUESTION ANSWER="1" ID="9" PLATFORM="true">
				<QUESTION Lane="0" Type="Image" Value="40/80">
		<DISPLAY><![CDATA[fluency/data/images/407d034f74473dd2364dae4e6d4eaf47.png]]></DISPLAY> 
				</QUESTION>
			</QUESTION>
			<QUESTION ANSWER="1" ID="10" PLATFORM="true">
				<QUESTION Lane="0" Type="Image" Value="20/10">
		<DISPLAY><![CDATA[fluency/data/images/65aa2586195b641fc8ba72ad7d8bf3d6.png]]></DISPLAY> 
				</QUESTION>
			</QUESTION>
		</PROBLEM_SUBSET>
 </PROBLEM_SET>

</GAME_DATA>
</INPUT>