<dataset game_id="ft3_jungle" id="jungle_6378">
	<datafile id="jungle_6378_001" name="jungle_6378_001.xml"/>
	<datafile id="jungle_6378_002" name="jungle_6378_002.xml"/>
	<datafile id="jungle_6378_003" name="jungle_6378_003.xml"/>
	<datafile id="jungle_6378_004" name="jungle_6378_004.xml"/>
	<datafile id="jungle_6378_005" name="jungle_6378_005.xml"/>
	<datafile id="jungle_6378_006" name="jungle_6378_006.xml"/>
	<datafile id="jungle_6378_007" name="jungle_6378_007.xml"/>
	<datafile id="jungle_6378_008" name="jungle_6378_008.xml"/>
	<datafile id="jungle_6378_009" name="jungle_6378_009.xml"/>
	<datafile id="jungle_6378_010" name="jungle_6378_010.xml"/>
</dataset>
